MANIFEST.in
README.txt
setup.py
kafx/__init__.py
kafx/cairodraw.py
kafx/compilar.py
kafx/flicker.py
kafx/kafx.py
kafx/kafx_gui.py
kafx/kafx_main.py
kafx/myconfig.py
kafx/myconfig2.py
kafx/slideass.py
kafx.egg-info/PKG-INFO
kafx.egg-info/SOURCES.txt
kafx.egg-info/dependency_links.txt
kafx.egg-info/not-zip-safe
kafx.egg-info/requires.txt
kafx.egg-info/top_level.txt
kafx/extras/__init__.py
kafx/fxs/__init__.py
kafx/fxs/not_so_simple.py
kafx/fxs/simple.py
kafx/fxs/simple2.py
kafx/fxs/simple3.py
kafx/fxs/Abelkm/BSFLS.py
kafx/fxs/Abelkm/__init__.py
kafx/fxs/Abelkm/clannad_op1.py
kafx/fxs/Abelkm/decode.py
kafx/fxs/Abelkm/dgray1.py
kafx/fxs/Abelkm/dgraymanop3_rw.py
kafx/fxs/Abelkm/ed2dragonaut.py
kafx/fxs/Abelkm/fairy_tail_op3.py
kafx/fxs/Abelkm/oreimo6.py
kafx/fxs/Abelkm/rai.py
kafx/fxs/Abelkm/testo.py
kafx/fxs/timh/__init__.py
kafx/fxs/timh/tim1.py
kafx/libs/Copiadephysics2.py
kafx/libs/__init__.py
kafx/libs/asslib.py
kafx/libs/audio.py
kafx/libs/common.py
kafx/libs/figures.py
kafx/libs/physics.py
kafx/libs/video.py
kafx/libs/draw/__init__.py
kafx/libs/draw/adv_a.py
kafx/libs/draw/adv_b.py
kafx/libs/draw/advanced.py
kafx/libs/draw/basic.py
kafx/libs/draw/extra.py