Metadata-Version: 1.1
Name: kafx
Version: 1.6.2
Summary: A software for creating Karaoke Effects (vector graphics animation on video)
Home-page: http://kafx.com.ar
Author: Jerónimo Barraco Mármol
Author-email: jerobarraco@yahoo.com.ar
License: GNU LGPL
Download-URL: http://kafx.com.ar
Keywords: kafx cairo python video audio text karaoke .ass
Platform: Platform Independent
Classifier: Operating System :: OS Independent
Classifier: Programming Language :: Python
Classifier: Programming Language :: Python :: 2
Classifier: Natural Language :: Spanish
Classifier: Development Status :: 5 - Production/Stable
Classifier: Intended Audience :: Developers
Classifier: Topic :: Multimedia
Provides: kafx
